data_diff/__init__.py
data_diff/__main__.py
data_diff/abcs/__init__.py
data_diff/abcs/compiler.py
data_diff/abcs/database_types.py
data_diff/config.py
data_diff/databases/__init__.py
data_diff/databases/_connect.py
data_diff/databases/base.py
data_diff/databases/bigquery.py
data_diff/databases/clickhouse.py
data_diff/databases/databricks.py
data_diff/databases/duckdb.py
data_diff/databases/mssql.py
data_diff/databases/mysql.py
data_diff/databases/oracle.py
data_diff/databases/postgresql.py
data_diff/databases/presto.py
data_diff/databases/redis.py
data_diff/databases/redshift.py
data_diff/databases/snowflake.py
data_diff/databases/sybase.py
data_diff/databases/trino.py
data_diff/databases/vertica.py
data_diff/diff_tables.py
data_diff/errors.py
data_diff/format.py
data_diff/hashdiff_tables.py
data_diff/info_tree.py
data_diff/joindiff_tables.py
data_diff/lexicographic_space.py
data_diff/parse_time.py
data_diff/py.typed
data_diff/queries/__init__.py
data_diff/queries/api.py
data_diff/queries/ast_classes.py
data_diff/queries/base.py
data_diff/queries/extras.py
data_diff/query_utils.py
data_diff/schema.py
data_diff/table_segment.py
data_diff/thread_utils.py
data_diff/utils.py
data_diff/version.py
dcs_core/__init__.py
dcs_core/__main__.py
dcs_core/__version__.py
dcs_core/cli/__init__.py
dcs_core/cli/cli.py
dcs_core/core/__init__.py
dcs_core/core/common/__init__.py
dcs_core/core/common/errors.py
dcs_core/core/common/models/__init__.py
dcs_core/core/common/models/configuration.py
dcs_core/core/common/models/dashboard.py
dcs_core/core/common/models/data_source_resource.py
dcs_core/core/common/models/metric.py
dcs_core/core/common/models/profile.py
dcs_core/core/common/models/validation.py
dcs_core/core/common/models/widget.py
dcs_core/core/configuration/__init__.py
dcs_core/core/configuration/config_loader.py
dcs_core/core/configuration/configuration_parser.py
dcs_core/core/configuration/configuration_parser_arc.py
dcs_core/core/datasource/__init__.py
dcs_sdk-1.7.1.dist-info/METADATA
dcs_sdk-1.7.1.dist-info/WHEEL
dcs_sdk-1.7.1.dist-info/entry_points.txt
dcs_sdk-1.7.1.dist-info/RECORD
