Metadata-Version: 2.4
Name: dcs-sdk
Version: 1.7.1
Summary: SDK for DataChecks
Author: Waterdip Labs
Author-email: hello@waterdip.ai
Requires-Python: >=3.10,<3.13
Classifier: Programming Language :: Python :: 3
Classifier: Programming Language :: Python :: 3.10
Classifier: Programming Language :: Python :: 3.11
Classifier: Programming Language :: Python :: 3.12
Provides-Extra: all-dbs
Provides-Extra: bigquery
Provides-Extra: clickhouse
Provides-Extra: databricks
Provides-Extra: db2
Provides-Extra: elasticsearch
Provides-Extra: impyla
Provides-Extra: mssql
Provides-Extra: mysql
Provides-Extra: opensearch
Provides-Extra: oracle
Provides-Extra: postgresql
Provides-Extra: preql
Provides-Extra: presto
Provides-Extra: redshift
Provides-Extra: snowflake
Provides-Extra: spark
Provides-Extra: sybase
Provides-Extra: trino
Provides-Extra: vertica
Requires-Dist: attrs (>=23.1.0)
Requires-Dist: azure-identity (>=1.25.1,<2.0.0)
Requires-Dist: azure-storage-blob (>=12.27.1,<13.0.0)
Requires-Dist: click (>=8.1)
Requires-Dist: clickhouse-driver (>=0.2.9) ; extra == "clickhouse" or extra == "all-dbs"
Requires-Dist: cryptography (>=44.0.1) ; extra == "snowflake" or extra == "all-dbs"
Requires-Dist: databricks-sql-connector (>=3.3.0,<4.0.0) ; extra == "databricks" or extra == "all-dbs"
Requires-Dist: dsnparse (<0.2.0)
Requires-Dist: duckdb (>=0.9.0)
Requires-Dist: elasticsearch (>=9.1.0,<10.0.0) ; extra == "elasticsearch" or extra == "all-dbs"
Requires-Dist: google-cloud-bigquery (>=3.31.0,<4.0.0) ; extra == "bigquery" or extra == "all-dbs"
Requires-Dist: h11 (>=0.16.0,<0.17.0)
Requires-Dist: ibm-db (>=3.2.3,<4.0.0) ; extra == "db2" or extra == "all-dbs"
Requires-Dist: ibm-db-sa (>=0.4.1,<0.5.0) ; extra == "db2" or extra == "all-dbs"
Requires-Dist: impyla (>=0.20.0,<0.21.0) ; extra == "impyla" or extra == "all-dbs"
Requires-Dist: jinja2 (>=3.1.6,<4.0.0)
Requires-Dist: keyring (>=25.3.0)
Requires-Dist: loguru (==0.7.2)
Requires-Dist: mashumaro[msgpack] (>=2.9,<3.11.0)
Requires-Dist: mysql-connector-python (>=9.0.1) ; extra == "mysql" or extra == "all-dbs"
Requires-Dist: nltk (>=3.9.1,<4.0.0)
Requires-Dist: numpy (==1.26.4)
Requires-Dist: opensearch-py (>=2.2.0,<3.0.0) ; extra == "opensearch" or extra == "all-dbs"
Requires-Dist: oracledb (>=2.4.1) ; extra == "oracle" or extra == "all-dbs"
Requires-Dist: packaging (>=24.1,<25.0)
Requires-Dist: preql (>=0.2.19) ; extra == "preql" or extra == "all-dbs"
Requires-Dist: presto-python-client (>=0.8.4) ; extra == "presto" or extra == "all-dbs"
Requires-Dist: protobuf (>=5.29.5,<6.0.0)
Requires-Dist: psycopg2-binary (>=2.9.9,<3.0.0) ; extra == "postgresql" or extra == "redshift" or extra == "all-dbs"
Requires-Dist: pydantic (>=1.10.12)
Requires-Dist: pymysql[rsa] (>=1.1.0,<2.0.0) ; extra == "mysql" or extra == "all-dbs"
Requires-Dist: pyodbc (>=4.0.39) ; extra == "mssql" or extra == "sybase" or extra == "all-dbs"
Requires-Dist: pyparsing (>=3.1.1,<4.0.0)
Requires-Dist: pyspark (>=3.2.1,<4.0.0) ; extra == "spark" or extra == "all-dbs"
Requires-Dist: python-dateutil (>=2.8.2,<3.0.0)
Requires-Dist: python-dotenv (>=1.0.1,<2.0.0)
Requires-Dist: pytz (>=2024.1)
Requires-Dist: pyyaml (>=6.0.1,<7.0.0)
Requires-Dist: redis[hiredis] (>=5.2.1,<6.0.0)
Requires-Dist: requests (>=2.32.4,<3.0.0)
Requires-Dist: rich (>=13.8.0)
Requires-Dist: setuptools (>=78.1.1)
Requires-Dist: snowflake-connector-python (>=3.17.2) ; extra == "snowflake" or extra == "all-dbs"
Requires-Dist: snowflake-sqlalchemy (>=1.5.3,<2.0.0) ; extra == "snowflake" or extra == "all-dbs"
Requires-Dist: sqlalchemy (>=2.0.14,<2.1.0)
Requires-Dist: sqlalchemy-bigquery (>=1.8.0,<2.0.0) ; extra == "bigquery" or extra == "all-dbs"
Requires-Dist: sqlalchemy-sybase (>=2.0.0,<3.0.0) ; extra == "sybase" or extra == "all-dbs"
Requires-Dist: tabulate (>=0.9.0)
Requires-Dist: toml (>=0.10.2)
Requires-Dist: tornado (>=6.5,<7.0)
Requires-Dist: trino (>=0.314.0) ; extra == "trino" or extra == "all-dbs"
Requires-Dist: typing-extensions (>=4.0.1)
Requires-Dist: urllib3 (>=2.5.0,<3.0.0)
Requires-Dist: vertica-python (>=1.4.0) ; extra == "vertica" or extra == "all-dbs"
